pyspark_spy/__init__.py
pyspark_spy/classes.py
pyspark_spy/interface.py
pyspark_spy/listeners.py
pyspark_spy/util.py
pyspark_spy-1.0.2.dist-info/LICENSE
pyspark_spy-1.0.2.dist-info/WHEEL
pyspark_spy-1.0.2.dist-info/METADATA
pyspark_spy-1.0.2.dist-info/RECORD
