Metadata-Version: 2.1
Name: pyspark-spy
Version: 1.0.2
Summary: Collect and aggregate on spark events for profitz. In 🐍 way!
Home-page: https://github.com/sashgorokhov/pyspark-spy
License: MIT
Author: Alexander Gorokhov
Author-email: sashgorokhov@gmail.com
Requires-Python: >=3.5
Classifier: License :: OSI Approved :: MIT License
Classifier: Programming Language :: Python :: 3
Classifier: Programming Language :: Python :: 3.5
Classifier: Programming Language :: Python :: 3.6
Classifier: Programming Language :: Python :: 3.7
Classifier: Programming Language :: Python :: 3.8
Classifier: Programming Language :: Python :: 3.9
Requires-Dist: pyspark (>=2.0.0)
